leadrouter/__init__.py
leadrouter/alerts.py
leadrouter/client.py
leadrouter/cmd.py
leadrouter/publisher.py
leadrouter/sentry.py
leadrouter/subscriber.py
leadrouter/timestamp.py
leadrouter-1.0.1.dist-info/DESCRIPTION.rst
leadrouter-1.0.1.dist-info/METADATA
leadrouter-1.0.1.dist-info/RECORD
leadrouter-1.0.1.dist-info/WHEEL
leadrouter-1.0.1.dist-info/entry_points.txt
leadrouter-1.0.1.dist-info/metadata.json
leadrouter-1.0.1.dist-info/top_level.txt
