Metadata-Version: 2.0
Name: leadrouter
Version: 1.0.1
Summary: Python Client to Real Geeks REST API
Home-page: https://github.com/RealGeeks/lead_router.py
Author: Igor Sobreira
Author-email: igor@realgeeks.com
License: MIT
Platform: UNKNOWN
Classifier: Development Status :: 5 - Production/Stable
Classifier: Intended Audience :: Developers
Classifier: Programming Language :: Python :: 2
Classifier: Programming Language :: Python :: 2.6
Classifier: Programming Language :: Python :: 2.7
Requires-Dist: beanstalkc
Requires-Dist: click
Requires-Dist: pyyaml
Requires-Dist: raven
Requires-Dist: requests
